odoo/addons/website_oca_integrator/README.rst
odoo/addons/website_oca_integrator/__init__.py
odoo/addons/website_oca_integrator/__manifest__.py
odoo/addons/website_oca_integrator/controllers/__init__.py
odoo/addons/website_oca_integrator/controllers/main.py
odoo/addons/website_oca_integrator/controllers/member.py
odoo/addons/website_oca_integrator/controllers/portal.py
odoo/addons/website_oca_integrator/controllers/website_sale.py
odoo/addons/website_oca_integrator/data/ir_cron.xml
odoo/addons/website_oca_integrator/demo/github_repository_branch.xml
odoo/addons/website_oca_integrator/demo/odoo_author.xml
odoo/addons/website_oca_integrator/demo/product_template.xml
odoo/addons/website_oca_integrator/demo/res_partner.xml
odoo/addons/website_oca_integrator/demo/res_users.xml
odoo/addons/website_oca_integrator/models/__init__.py
odoo/addons/website_oca_integrator/models/contributor_module_line.py
odoo/addons/website_oca_integrator/models/odoo_author.py
odoo/addons/website_oca_integrator/models/res_partner.py
odoo/addons/website_oca_integrator/models/sponsorship.py
odoo/addons/website_oca_integrator/security/ir.model.access.csv
odoo/addons/website_oca_integrator/static/description/icon.png
odoo/addons/website_oca_integrator/static/src/js/integrator_portal.js
odoo/addons/website_oca_integrator/static/src/js/integrator_portal_tour.js
odoo/addons/website_oca_integrator/tests/__init__.py
odoo/addons/website_oca_integrator/tests/test_github_contributor_module.py
odoo/addons/website_oca_integrator/tests/test_integrator.py
odoo/addons/website_oca_integrator/tests/test_integrator_controller.py
odoo/addons/website_oca_integrator/tests/test_ui_portal.py
odoo/addons/website_oca_integrator/views/assets.xml
odoo/addons/website_oca_integrator/views/view_odoo_author.xml
odoo/addons/website_oca_integrator/views/view_portal_templates.xml
odoo/addons/website_oca_integrator/views/view_res_partner.xml
odoo/addons/website_oca_integrator/views/website_oca_integrator_contributor_templates.xml
odoo11_addon_website_oca_integrator-11.0.1.0.1.99.dev1.dist-info/METADATA
odoo11_addon_website_oca_integrator-11.0.1.0.1.99.dev1.dist-info/WHEEL
odoo11_addon_website_oca_integrator-11.0.1.0.1.99.dev1.dist-info/top_level.txt
odoo11_addon_website_oca_integrator-11.0.1.0.1.99.dev1.dist-info/RECORD
